{
  "definitions": [
    {
      "title": "DM Image",
      "id": "dm-image",
      "plugins": {
        "xwalk": {
          "page": {
            "resourceType": "core/franklin/components/block/v1/block",
            "template": {
              "name": "DM Image",
              "model": "dm-image"
            }
          }
        }
      }
    }
  ],
  "models": [
    {
      "id": "dm-image",
      "fields": [
        {
          "component": "custom-asset-namespace:custom-asset",
          "name": "image",
          "label": "DM Image",
          "description": "Select a Dynamic Media delivery URL via the custom asset picker.",
          "configUrl": "https://main--newedsue--RitwikSrivastava.aem.page/tools/asset-selector/image.config.json",
          "valueType": "string"
        },
        {
          "component": "custom-asset-namespace:custom-asset-mimetype",
          "valueType": "string",
          "name": "imageMimeType"
        },
        {
          "component": "text",
          "valueType": "string",
          "name": "imageAlt",
          "label": "Alt",
          "value": ""
        },
        {
          "component": "text",
          "valueType": "string",
          "name": "origin",
          "label": "DM Origin (optional)",
          "value": ""
        },
        {
          "component": "text",
          "valueType": "string",
          "name": "priority",
          "label": "Priority (true/false)",
          "value": ""
        },
        {
          "component": "text",
          "valueType": "string",
          "name": "preset",
          "label": "Preset (optional)",
          "value": ""
        },
        {
          "component": "text",
          "valueType": "string",
          "name": "smartCrop",
          "label": "Smart Crop (optional)",
          "value": ""
        },
        {
          "component": "text",
          "valueType": "string",
          "name": "role",
          "label": "Role (optional)",
          "value": ""
        }
      ]
    }
  ],
  "filters": []
}
